Workbook

Sheet README
A1: Data-Centre Feasibility Index for Indian States, 2026
A3: Purpose: rank States/UTs on their suitability for new data-centre capacity, combining water, power, people and disaster-risk indicators.
A5: Sheets
A6: Data_All: every indicator for all 36 States/UTs, as published (blue = source values).
A7: Weights: PCA-derived weights (from Python, documented) plus equal, pillar and custom weight sets. Edit the yellow custom row to test your own weights.
A8: Index: the 19 eligible states, normalised indicators and four index variants, all formula-driven.
A9: Sources: full citation for each indicator.
A11: Method
A12: 1. Screen: exclude States/UTs with groundwater stage of extraction above 90% (critical or over-exploited) and grids under 10 TWh/yr or without a 20 MW tariff; islands excluded. 19 states remain.
A13: 2. Normalise: min–max to 0–1 across the 19 states; direction set so 1 = most favourable. Electricity supply uses natural logs.
A14: 3. Weight: PCA on standardised indicators; 3 components with eigenvalue >1 retained (75.1% of variance); varimax rotation; each indicator weighted by its squared loading on its dominant component, scaled by that component's share (OECD/JRC composite-indicator handbook approach).
A15: 4. Score: Index = 100 × Σ(weight × normalised value).
... A19: PCA weights reflect how indicators co-vary across 19 states, not policy importance; with n=19 they are indicative. Hazard data pre-date 2019. State averages hide district hotspots (e.g. Bengaluru Urban, Chennai). Land, fibre/subsea-cable access and renewable availability are not included.

Sheet Data_All
A1: All indicators, all States/UTs
A2: Blue = source values; black = formulas. See Sources sheet for each column.
A4: State / UT | B4: Status in index | C4: GW recharge (BCM) | D4: GW extractable (BCM) | E4: GW extraction (BCM) | F4: Stage of extraction (%) | G4: GW headroom (BCM) | H4: Power supplied 2024-25 (MU) | I4: Energy shortfall (%) | J4: Tariff 20 MW @33kV (₹/kWh) | K4: Adults 15+ with diploma/degree (%) | L4: Urban regular salary (₹/month) | M4: Hazard index (0–10) | N4: Disaster Risk Index (0–100)
A5: Andhra Pradesh | B5: Ranked | C5: 26.34 | D5: 25.02 | E5: 7.88 | F5: 31.51 | G5: =D5-E5 -> 17.14 | H5: 79025 | I5: 0 | J5: 7.36 | K5: 14.8 | L5: 25574 | M5: 4.25 | N5: 27.58
A6: Arunachal Pradesh | B6: Not ranked (scale/data) | C6: 3.69 | D6: 3.29 | E6: 0.01 | F6: 0.41 | G6: =D6-E6 -> 3.28 | H6: 1050 | I6: 0 | J6: 4.15 | K6: 12.6 | L6: 34678 | M6: 2.76 | N6: 15.63
A7: Assam | B7: Ranked | C7: 26.36 | D7: 20.29 | E7: 2.93 | F7: 14.45 | G7: =D7-E7 -> 17.36 | H7: 12837 | I7: 0 | J7: 8.97 | K7: 8.5 | L7: 27299 | M7: 3.03 | N7: 28.75
A8: Bihar | B8: Ranked | C8: 34.51 | D8: 31.32 | E8: 14.47 | F8: 46.2 | G8: =D8-E8 -> 16.85 | H8: 44217 | I8: 0.4 | J8: 10.62 | K8: 9.7 | L8: 24968 | M8: 3.13 | N8: 24.99
A9: Chhattisgarh | B9: Ranked | C9: 14.3 | D9: 13.07 | E9: 6.3 | F9: 48.18 | G9: =D9-E9 -> 6.77 | H9: 43180 | I9: 0.1 | J9: 9.69 | K9: 11.9 | L9: 21042 | M9: 2.25 | N9: 14.2
A10: Goa | B10: Not ranked (scale/data) | C10: 0.38 | D10: 0.31 | E10: 0.07 | F10: 23.3 | G10: =D10-E10 -> 0.24 | H10: 5411 | I10: 0 | J10: 7.12 | K10: 21.8 | L10: 30852 | M10: 1.96 | N10: 10.35
A11: Gujarat | B11: Ranked | C11: 27.58 | D11: 25.61 | E11: 14.33 | F11: 55.95 | G11: =D11-E11 -> 11.28 | H11: 151875 | I11: 0 | J11: 6.22 | K11: 14.9 | L11: 21805 | M11: 3.66 | N11: 27.44
A12: Haryana | B12: Screened out (groundwater) | C12: 10.27 | D12: 9.3 | E12: 12.72 | F12: 136.75 | G12: =D12-E12 -> -3.42 | H12: 70120 | I12: 0 | J12: 8.61 | K12: 21.3 | L12: 31306 | M12: 2.26 | N12: 14.76
A13: Himachal Pradesh | B13: Ranked | C13: 1.12 | D13: 1.01 | E13: 0.39 | F13: 38.5 | G13: =D13-E13 -> 0.62 | H13: 13526 | I13: 0.3 | J13: 8.07 | K13: 22.7 | L13: 27878 | M13: 3.03 | N13: 15.63
A14: Jharkhand | B14: Ranked | C14: 6.15 | D14: 5.63 | E14: 1.85 | F14: 32.89 | G14: =D14-E14 -> 3.78 | H14: 15126 | I14: 0.5 | J14: 8.82 | K14: 9.9 | L14: 30055 | M14: 2.46 | N14: 17.03
A15: Karnataka | B15: Ranked | C15: 19.27 | D15: 17.41 | E15: 11.58 | F15: 66.49 | G15: =D15-E15 -> 5.83 | H15: 92446 | I15: 0 | J15: 8.1 | K15: 17.4 | L15: 30471 | M15: 2.78 | N15: 29.82
A16: Kerala | B16: Ranked | C16: 5.45 | D16: 4.93 | E16: 2.46 | F16: 49.95 | G16: =D16-E16 -> 2.47 | H16: 31616 | I16: 0 | J16: 7.63 | K16: 25 | L16: 28475 | M16: 2.97 | N16: 13.75
... A18: Maharashtra | B18: Ranked | C18: 33.89 | D18: 31.99 | E18: 16.57 | F18: 51.79 | G18: =D18-E18 -> 15.42 | H18: 201757 | I18: 0 | J18: 13.18 | K18: 20.3 | L18: 30493 | M18: 4.07 | N18: 54.75
A19: Manipur | B19: Not ranked (scale/data) | C19: 0.44 | D19: 0.4 | E19: 0.04 | F19: 9.09 | G19: =D19-E19 -> 0.36 | H19: 1068 | I19: 0.9 | J19: n/a | K19: 21.7 | L19: 32999 | M19: 2.96 | N19: 16.11
A20: Meghalaya | B20: Not ranked (scale/data) | C20: 1.84 | D20: 1.54 | E20: 0.08 | F20: 5.24 | G20: =D20-E20 -> 1.46 | H20: 2046 | I20: 0 | J20: 11.15 | K20: 9.2 | L20: 25747 | M20: 2.65 | N20: 15.88
A21: Mizoram | B21: Not ranked (scale/data) | C21: 0.21 | D21: 0.19 | E21: 0.01 | F21: 4.03 | G21: =D21-E21 -> 0.18 | H21: 709 | I21: 0 | J21: n/a | K21: 17.8 | L21: 37626 | M21: 3.06 | N21: 14.71
A22: Nagaland | B22: Not ranked (scale/data) | C22: 0.55 | D22: 0.5 | E22: 0.02 | F22: 4.72 | G22: =D22-E22 -> 0.48 | H22: 938 | I22: 0 | J22: n/a | K22: 14.5 | L22: 35430 | M22: 2.82 | N22: 15.92
A23: Odisha | B23: Ranked | C23: 17.44 | D23: 16.02 | E23: 7.81 | F23: 48.75 | G23: =D23-E23 -> 8.21 | H23: 42858 | I23: 0.1 | J23: 6.95 | K23: 11.1 | L23: 24955 | M23: 3.8 | N23: 22.68
A24: Punjab | B24: Screened out (groundwater) | C24: 18.6 | D24: 16.8 | E24: 26.27 | F24: 156.36 | G24: =D24-E24 -> -9.47 | H24: 77423 | I24: 0 | J24: 9.21 | K24: 12.9 | L24: 18682 | M24: 2.67 | N24: 21.29
A25: Rajasthan | B25: Screened out (groundwater) | C25: 12.87 | D25: 11.62 | E25: 17.1 | F25: 147.11 | G25: =D25-E25 -> -5.48 | H25: 113529 | I25: 0.3 | J25: 8.11 | K25: 15.7 | L25: 25950 | M25: 2.29 | N25: 30.04
A26: Sikkim | B26: Not ranked (scale/data) | C26: 0.24 | D26: 0.22 | E26: 0.01 | F26: 5.87 | G26: =D26-E26 -> 0.21 | H26: 574 | I26: 0 | J26: n/a | K26: 17.5 | L26: 29848 | M26: 2.12 | N26: 11.11
A27: Tamil Nadu | B27: Ranked | C27: 22.61 | D27: 20.46 | E27: 15.04 | F27: 73.5 | G27: =D27-E27 -> 5.42 | H27: 130408 | I27: 0 | J27: 9.49 | K27: 24.7 | L27: 26223 | M27: 2.84 | N27: 22.36
A28: Telangana | B28: Ranked | C28: 21.93 | D28: 19.84 | E28: 9.26 | F28: 46.69 | G28: =D28-E28 -> 10.58 | H28: 88258 | I28: 0 | J28: 8.79 | K28: 18.3 | L28: 29697 | M28: 2 | N28: 18.25
A29: Tripura | B29: Not ranked (scale/data) | C29: 1.53 | D29: 1.24 | E29: 0.12 | F29: 10.06 | G29: =D29-E29 -> 1.12 | H29: 1939 | I29: 0 | J29: n/a | K29: 9.4 | L29: 24702 | M29: 2.81 | N29: 15.99
A30: Uttar Pradesh | B30: Ranked | C30: 73.39 | D30: 66.97 | E30: 46.89 | F30: 70 | G30: =D30-E30 -> 20.08 | H30: 164786 | I30: 0.2 | J30: 8.91 | K30: 14.6 | L30: 21940 | M30: 2.62 | N30: 42.24
A31: Uttarakhand | B31: Ranked | C31: 2.13 | D31: 1.95 | E31: 1.05 | F31: 53.92 | G31: =D31-E31 -> 0.9 | H31: 16727 | I31: 0.3 | J31: 9.95 | K31: 18 | L31: 20912 | M31: 3.38 | N31: 18.16
A32: West Bengal | B32: Ranked | C32: 25.85 | D32: 23.5 | E32: 10.62 | F32: 45.19 | G32: =D32-E32 -> 12.88 | H32: 71085 | I32: 0.1 | J32: 9.04 | K32: 10.9 | L32: 19019 | M32: 4.31 | N32: 51.78
A33: Andaman and Nicobar | B33: Not ranked (scale/data) | C33: 0.38 | D33: 0.35 | E33: 0.01 | F33: 2.27 | G33: =D33-E33 -> 0.34 | H33: 413 | I33: 2.9 | J33: 13.14 | K33: 14.6 | L33: 33787 | M33: 3.15 | N33: 13.23
A34: Chandigarh | B34: Not ranked (scale/data) | C34: 0.05 | D34: 0.05 | E34: 0.03 | F34: 67 | G34: =D34-E34 -> 0.02 | H34: 1952 | I34: 0 | J34: 4.98 | K34: 30 | L34: 29211 | M34: 1.5 | N34: 10.94
A35: Dadra and Nagar Haveli and Daman and Diu | B35: Ranked | C35: 0.13 | D35: 0.12 | E35: 0.05 | F35: 40.45 | G35: =D35-E35 -> 0.07 | H35: 10852 | I35: 0 | J35: 6.29 | K35: 12.6 | L35: 18789 | M35: 2.005 | N35: 10.055
A36: Delhi | B36: Screened out (groundwater) | C36: 0.38 | D36: 0.35 | E36: 0.32 | F36: 92.1 | G36: =D36-E36 -> 0.03 | H36: 38243 | I36: 0 | J36: 9.33 | K36: 27.8 | L36: 30674 | M36: 1.85 | N36: 14.43
A37: Jammu and Kashmir | B37: Ranked | C37: 2.3 | D37: 2.07 | E37: 0.51 | F37: 24.73 | G37: =D37-E37 -> 1.56 | H37: 20283 | I37: 0.4 | J37: 5.18 | K37: 14.1 | L37: 29088 | M37: 2.26 | N37: 14.56
A38: Ladakh | B38: Not ranked (scale/data) | C38: 0.07 | D38: 0.06 | E38: 0.02 | F38: 30.93 | G38: =D38-E38 -> 0.04 | H38: n/a | I38: n/a | J38: 5.95 | K38: 13.6 | L38: 32971 | M38: 2.26 | N38: 14.56
A39: Lakshadweep | B39: Not ranked (scale/data) | C39: 0.01 | D39: 0.01 | E39: 0 | F39: 57.79 | G39: =D39-E39 -> 0.01 | H39: 68 | I39: 0 | J39: n/a | K39: 17.6 | L39: 31121 | M39: 1.58 | N39: 9.72
A40: Puducherry | B40: Not ranked (scale/data) | C40: 0.19 | D40: 0.17 | E40: 0.13 | F40: 75.98 | G40: =D40-E40 -> 0.04 | H40: 3549 | I40: 0 | J40: 7.88 | K40: 34.4 | L40: 31652 | M40: 1.99 | N40: 10.41
A42: Ladakh power supply is reported within Jammu & Kashmir. Hazard/DRI: Ladakh uses J&K values; DNH&DD averages the two former UTs. Tariff n/a = no rate for this category in CEA table.

Sheet Weights
A1: Indicator weights
A3: Weight set | B3: Stage of extraction | C3: GW headroom | D3: Tariff | E3: Power supplied (log) | F3: Diploma/degree share | G3: Urban salary | H3: Hazard (or DRI) | I3: Sum
A4: PCA (main) | B4: 0.2176 | C4: 0.1974 | D4: 0.0813 | E4: 0.1196 | F4: 0.0752 | G4: 0.2056 | H4: 0.1032 | I4: =SUM(B4:H4) -> 0.9999
A5: Equal indicator | B5: 0.1429 | C5: 0.1429 | D5: 0.1429 | E5: 0.1429 | F5: 0.1429 | G5: 0.1429 | H5: 0.1429 | I5: =SUM(B5:H5) -> 1.0003
A6: Equal pillar (water, power, people, risk) | B6: 0.125 | C6: 0.125 | D6: 0.125 | E6: 0.125 | F6: 0.125 | G6: 0.125 | H6: 0.25 | I6: =SUM(B6:H6) -> 1
A7: Custom (edit me) | B7: 0.2 | C7: 0.15 | D7: 0.15 | E7: 0.1 | F7: 0.15 | G7: 0.1 | H7: 0.15 | I7: =SUM(B7:H7) -> 1
A9: Direction (1 = higher is better) | B9: lower | C9: higher | D9: lower | E9: higher | F9: higher | G9: lower | H9: lower
A11: PCA diagnostics (computed in Python/numpy on standardised indicators, n=19)
A12: Eigenvalues | B12: 2.391 | C12: 1.702 | D12: 1.165 | E12: 0.783 | F12: 0.677 | G12: 0.205 | H12: 0.078
A13: Share of variance | B13: =B12/SUM($B$12:$H$12) -> 0.34152264 | C13: =C12/SUM($B$12:$H$12) -> 0.24310813 | D13: =D12/SUM($B$12:$H$12) -> 0.1664048 | E13: =E12/SUM($B$12:$H$12) -> 0.11184117 | F13: =F12/SUM($B$12:$H$12) -> 0.096700471 | G13: =G12/SUM($B$12:$H$12) -> 0.029281531 | H13: =H12/SUM($B$12:$H$12) -> 0.011141266
A15: Rotated loadings (varimax) | B15: Component 1 | C15: Component 2 | D15: Component 3
A16: Stage of extraction | B16: -0.043 | C16: 0.953 | D16: 0.131
A17: GW headroom | B17: 0.908 | C17: 0.01 | D17: -0.135
A18: Tariff | B18: -0.582 | C18: 0.247 | D18: -0.345
A19: Power supplied (log) | B19: 0.578 | C19: -0.707 | D19: 0
A20: Diploma/degree share | B20: -0.311 | C20: -0.645 | D20: 0.56
A21: Urban salary | B21: 0.015 | C21: -0.123 | D21: -0.926
A22: Hazard (or DRI) | B22: -0.656 | C22: 0.053 | D22: 0.03
A24: The custom row (yellow) feeds the 'Custom index' column on the Index sheet. Weights should sum to 100%.

Sheet Index
A1: Feasibility index — 19 eligible states
A2: Green = linked from Data_All. Normalised values: 1 = most favourable among the 19.
A4: State | B4: Stage of extraction (%) | C4: GW headroom (BCM) | D4: Tariff (₹/kWh) | E4: Power supplied (MU) | F4: Diploma/degree (%) | G4: Urban salary (₹) | H4: Hazard index | I4: DRI | J4: N: SoE | K4: N: Headroom | L4: N: Tariff | M4: N: Supply (log) | N4: N: Skills | O4: N: Wage | P4: N: Hazard | Q4: N: DRI | R4: PCA index | S4: Rank | T4: Equal-indicator index | U4: Rank | V4: Equal-pillar index | W4: Rank | X4: DRI-swap index | Y4: Rank | Z4: Top 8 in (of 4) | AA4: Custom index | AB4: Rank
A5: Andhra Pradesh | B5: =INDEX(Data_All!$F$5:$F$40,MATCH($A5,Data_All!$A$5:$A$40,0)) -> 31.51 | C5: =INDEX(Data_All!$G$5:$G$40,MATCH($A5,Data_All!$A$5:$A$40,0)) -> 17.14 | D5: =INDEX(Data_All!$J$5:$J$40,MATCH($A5,Data_All!$A$5:$A$40,0)) -> 7.36 | E5: =INDEX(Data_All!$H$5:$H$40,MATCH($A5,Data_All!$A$5:$A$40,0)) -> 79025 | F5: =INDEX(Data_All!$K$5:$K$40,MATCH($A5,Data_All!$A$5:$A$40,0)) -> 14.8 | G5: =INDEX(Data_All!$L$5:$L$40,MATCH($A5,Data_All!$A$5:$A$40,0)) -> 25574 | H5: =INDEX(Data_All!$M$5:$M$40,MATCH($A5,Data_All!$A$5:$A$40,0)) -> 4.25 | I5: =INDEX(Data_All!$N$5:$N$40,MATCH($A5,Data_All!$A$5:$A$40,0)) -> 27.58 | J5: =(MAX($B$5:$B$23)-B5)/(MAX($B$5:$B$23)-MIN($B$5:$B$23)) -> 0.71109229 | K5: =(C5-MIN($C$5:$C$23))/(MAX($C$5:$C$23)-MIN($C$5:$C$23)) -> 0.85307346 | L5: =(MAX($D$5:$D$23)-D5)/(MAX($D$5:$D$23)-MIN($D$5:$D$23)) -> 0.7275 | M5: =(LN(E5)-LN(MIN($E$5:$E$23)))/(LN(MAX($E$5:$E$23))-LN(MIN($E$5:$E$23))) -> 0.67930507 | N5: =(F5-MIN($F$5:$F$23))/(MAX($F$5:$F$23)-MIN($F$5:$F$23)) -> 0.38181818 | O5: =(MAX($G$5:$G$23)-G5)/(MAX($G$5:$G$23)-MIN($G$5:$G$23)) -> 0.42028366 | P5: =(MAX($H$5:$H$23)-H5)/(MAX($H$5:$H$23)-MIN($H$5:$H$23)) -> 0.025974026 | Q5: =(MAX($I$5:$I$23)-I5)/(MAX($I$5:$I$23)-MIN($I$5:$I$23)) -> 0.60789798 | R5: =100*SUMPRODUCT(J5:P5,Weights!$B$4:$H$4) -> 58.132459 | S5: =RANK(R5,$R$5:$R$23,0) -> 2 | T5: =100*SUMPRODUCT(J5:P5,Weights!$B$5:$H$5) -> 54.288377 | U5: =RANK(T5,$T$5:$T$23,0) -> 5 | V5: =100*SUMPRODUCT(J5:P5,Weights!$B$6:$H$6) -> 47.812759 | W5: =RANK(V5,$V$5:$V$23,0) -> 11 | X5: =100*(SUMPRODUCT(J5:O5,Weights!$B$4:$G$4)+Q5*Weights!$H$4) -> 64.137914 | Y5: =RANK(X5,$X$5:$X$23,0) -> 1 | Z5: =(S5<=8)+(U5<=8)+(W5<=8)+(Y5<=8) -> 3 | AA5: =100*SUMPRODUCT(J5:P5,Weights!$B$7:$H$7) -> 55.043218 | AB5: =RANK(AA5,$AA$5:$AA$23,0) -> 3
A6: Assam | B6: =INDEX(Data_All!$F$5:$F$40,MATCH($A6,Data_All!$A$5:$A$40,0)) -> 14.45 | C6: =INDEX(Data_All!$G$5:$G$40,MATCH($A6,Data_All!$A$5:$A$40,0)) -> 17.36 | D6: =INDEX(Data_All!$J$5:$J$40,MATCH($A6,Data_All!$A$5:$A$40,0)) -> 8.97 | E6: =INDEX(Data_All!$H$5:$H$40,MATCH($A6,Data_All!$A$5:$A$40,0)) -> 12837 | F6: =INDEX(Data_All!$K$5:$K$40,MATCH($A6,Data_All!$A$5:$A$40,0)) -> 8.5 | G6: =INDEX(Data_All!$L$5:$L$40,MATCH($A6,Data_All!$A$5:$A$40,0)) -> 27299 | H6: =INDEX(Data_All!$M$5:$M$40,MATCH($A6,Data_All!$A$5:$A$40,0)) -> 3.03 | I6: =INDEX(Data_All!$N$5:$N$40,MATCH($A6,Data_All!$A$5:$A$40,0)) -> 28.75 | J6: =(MAX($B$5:$B$23)-B6)/(MAX($B$5:$B$23)-MIN($B$5:$B$23)) -> 1 | K6: =(C6-MIN($C$5:$C$23))/(MAX($C$5:$C$23)-MIN($C$5:$C$23)) -> 0.86406797 | L6: =(MAX($D$5:$D$23)-D6)/(MAX($D$5:$D$23)-MIN($D$5:$D$23)) -> 0.52625 | M6: =(LN(E6)-LN(MIN($E$5:$E$23)))/(LN(MAX($E$5:$E$23))-LN(MIN($E$5:$E$23))) -> 0.057474729 | N6: =(F6-MIN($F$5:$F$23))/(MAX($F$5:$F$23)-MIN($F$5:$F$23)) -> 0 | O6: =(MAX($G$5:$G$23)-G6)/(MAX($G$5:$G$23)-MIN($G$5:$G$23)) -> 0.27289815 | P6: =(MAX($H$5:$H$23)-H6)/(MAX($H$5:$H$23)-MIN($H$5:$H$23)) -> 0.55411255 | Q6: =(MAX($I$5:$I$23)-I6)/(MAX($I$5:$I$23)-MIN($I$5:$I$23)) -> 0.58172055 | R6: =100*SUMPRODUCT(J6:P6,Weights!$B$4:$H$4) -> 55.11174 | S6: =RANK(R6,$R$5:$R$23,0) -> 5 | T6: =100*SUMPRODUCT(J6:P6,Weights!$B$5:$H$5) -> 46.796941 | U6: =RANK(T6,$T$5:$T$23,0) -> 12 | V6: =100*SUMPRODUCT(J6:P6,Weights!$B$6:$H$6) -> 47.861449 | W6: =RANK(V6,$V$5:$V$23,0) -> 10 | X6: =100*(SUMPRODUCT(J6:O6,Weights!$B$4:$G$4)+Q6*Weights!$H$4) -> 55.396654 | Y6: =RANK(X6,$X$5:$X$23,0) -> 5 | Z6: =(S6<=8)+(U6<=8)+(W6<=8)+(Y6<=8) -> 2 | AA6: =100*SUMPRODUCT(J6:P6,Weights!$B$7:$H$7) -> 52.470187 | AB6: =RANK(AA6,$AA$5:$AA$23,0) -> 7
A7: Bihar | B7: =INDEX(Data_All!$F$5:$F$40,MATCH($A7,Data_All!$A$5:$A$40,0)) -> 46.2 | C7: =INDEX(Data_All!$G$5:$G$40,MATCH($A7,Data_All!$A$5:$A$40,0)) -> 16.85 | D7: =INDEX(Data_All!$J$5:$J$40,MATCH($A7,Data_All!$A$5:$A$40,0)) -> 10.62 | E7: =INDEX(Data_All!$H$5:$H$40,MATCH($A7,Data_All!$A$5:$A$40,0)) -> 44217 | F7: =INDEX(Data_All!$K$5:$K$40,MATCH($A7,Data_All!$A$5:$A$40,0)) -> 9.7 | G7: =INDEX(Data_All!$L$5:$L$40,MATCH($A7,Data_All!$A$5:$A$40,0)) -> 24968 | H7: =INDEX(Data_All!$M$5:$M$40,MATCH($A7,Data_All!$A$5:$A$40,0)) -> 3.13 | I7: =INDEX(Data_All!$N$5:$N$40,MATCH($A7,Data_All!$A$5:$A$40,0)) -> 24.99 | J7: =(MAX($B$5:$B$23)-B7)/(MAX($B$5:$B$23)-MIN($B$5:$B$23)) -> 0.46232007 | K7: =(C7-MIN($C$5:$C$23))/(MAX($C$5:$C$23)-MIN($C$5:$C$23)) -> 0.83858071 | L7: =(MAX($D$5:$D$23)-D7)/(MAX($D$5:$D$23)-MIN($D$5:$D$23)) -> 0.32 | M7: =(LN(E7)-LN(MIN($E$5:$E$23)))/(LN(MAX($E$5:$E$23))-LN(MIN($E$5:$E$23))) -> 0.48063534 | N7: =(F7-MIN($F$5:$F$23))/(MAX($F$5:$F$23)-MIN($F$5:$F$23)) -> 0.072727273 | O7: =(MAX($G$5:$G$23)-G7)/(MAX($G$5:$G$23)-MIN($G$5:$G$23)) -> 0.47206083 | P7: =(MAX($H$5:$H$23)-H7)/(MAX($H$5:$H$23)-MIN($H$5:$H$23)) -> 0.51082251 | Q7: =(MAX($I$5:$I$23)-I7)/(MAX($I$5:$I$23)-MIN($I$5:$I$23)) -> 0.66584629 | R7: =100*SUMPRODUCT(J7:P7,Weights!$B$4:$H$4) -> 50.487835 | S7: =RANK(R7,$R$5:$R$23,0) -> 9 | T7: =100*SUMPRODUCT(J7:P7,Weights!$B$5:$H$5) -> 45.115627 | U7: =RANK(T7,$T$5:$T$23,0) -> 13 | V7: =100*SUMPRODUCT(J7:P7,Weights!$B$6:$H$6) -> 45.849616 | W7: =RANK(V7,$V$5:$V$23,0) -> 12 | X7: =100*(SUMPRODUCT(J7:O7,Weights!$B$4:$G$4)+Q7*Weights!$H$4) -> 52.08768 | Y7: =RANK(X7,$X$5:$X$23,0) -> 8 | Z7: =(S7<=8)+(U7<=8)+(W7<=8)+(Y7<=8) -> 1 | AA7: =100*SUMPRODUCT(J7:P7,Weights!$B$7:$H$7) -> 44.905321 | AB7: =RANK(AA7,$AA$5:$AA$23,0) -> 14
A8: Chhattisgarh | B8: =INDEX(Data_All!$F$5:$F$40,MATCH($A8,Data_All!$A$5:$A$40,0)) -> 48.18 | C8: =INDEX(Data_All!$G$5:$G$40,MATCH($A8,Data_All!$A$5:$A$40,0)) -> 6.77 | D8: =INDEX(Data_All!$J$5:$J$40,MATCH($A8,Data_All!$A$5:$A$40,0)) -> 9.69 | E8: =INDEX(Data_All!$H$5:$H$40,MATCH($A8,Data_All!$A$5:$A$40,0)) -> 43180 | F8: =INDEX(Data_All!$K$5:$K$40,MATCH($A8,Data_All!$A$5:$A$40,0)) -> 11.9 | G8: =INDEX(Data_All!$L$5:$L$40,MATCH($A8,Data_All!$A$5:$A$40,0)) -> 21042 | H8: =INDEX(Data_All!$M$5:$M$40,MATCH($A8,Data_All!$A$5:$A$40,0)) -> 2.25 | I8: =INDEX(Data_All!$N$5:$N$40,MATCH($A8,Data_All!$A$5:$A$40,0)) -> 14.2 | J8: =(MAX($B$5:$B$23)-B8)/(MAX($B$5:$B$23)-MIN($B$5:$B$23)) -> 0.42878916 | K8: =(C8-MIN($C$5:$C$23))/(MAX($C$5:$C$23)-MIN($C$5:$C$23)) -> 0.33483258 | L8: =(MAX($D$5:$D$23)-D8)/(MAX($D$5:$D$23)-MIN($D$5:$D$23)) -> 0.43625 | M8: =(LN(E8)-LN(MIN($E$5:$E$23)))/(LN(MAX($E$5:$E$23))-LN(MIN($E$5:$E$23))) -> 0.47251553 | N8: =(F8-MIN($F$5:$F$23))/(MAX($F$5:$F$23)-MIN($F$5:$F$23)) -> 0.20606061 | O8: =(MAX($G$5:$G$23)-G8)/(MAX($G$5:$G$23)-MIN($G$5:$G$23)) -> 0.80750171 | P8: =(MAX($H$5:$H$23)-H8)/(MAX($H$5:$H$23)-MIN($H$5:$H$23)) -> 0.89177489 | Q8: =(MAX($I$5:$I$23)-I8)/(MAX($I$5:$I$23)-MIN($I$5:$I$23)) -> 0.90726032 | R8: =100*SUMPRODUCT(J8:P8,Weights!$B$4:$H$4) -> 52.492973 | S8: =RANK(R8,$R$5:$R$23,0) -> 7 | T8: =100*SUMPRODUCT(J8:P8,Weights!$B$5:$H$5) -> 51.125683 | U8: =RANK(T8,$T$5:$T$23,0) -> 7 | V8: =100*SUMPRODUCT(J8:P8,Weights!$B$6:$H$6) -> 55.868742 | W8: =RANK(V8,$V$5:$V$23,0) -> 5 | X8: =100*(SUMPRODUCT(J8:O8,Weights!$B$4:$G$4)+Q8*Weights!$H$4) -> 52.652783 | Y8: =RANK(X8,$X$5:$X$23,0) -> 7 | Z8: =(S8<=8)+(U8<=8)+(W8<=8)+(Y8<=8) -> 4 | AA8: =100*SUMPRODUCT(J8:P8,Weights!$B$7:$H$7) -> 49.409727 | AB8: =RANK(AA8,$AA$5:$AA$23,0) -> 9
A9: Dadra and Nagar Haveli and Daman and Diu | B9: =INDEX(Data_All!$F$5:$F$40,MATCH($A9,Data_All!$A$5:$A$40,0)) -> 40.45 | C9: =INDEX(Data_All!$G$5:$G$40,MATCH($A9,Data_All!$A$5:$A$40,0)) -> 0.07 | D9: =INDEX(Data_All!$J$5:$J$40,MATCH($A9,Data_All!$A$5:$A$40,0)) -> 6.29 | E9: =INDEX(Data_All!$H$5:$H$40,MATCH($A9,Data_All!$A$5:$A$40,0)) -> 10852 | F9: =INDEX(Data_All!$K$5:$K$40,MATCH($A9,Data_All!$A$5:$A$40,0)) -> 12.6 | G9: =INDEX(Data_All!$L$5:$L$40,MATCH($A9,Data_All!$A$5:$A$40,0)) -> 18789 | H9: =INDEX(Data_All!$M$5:$M$40,MATCH($A9,Data_All!$A$5:$A$40,0)) -> 2.005 | I9: =INDEX(Data_All!$N$5:$N$40,MATCH($A9,Data_All!$A$5:$A$40,0)) -> 10.055 | J9: =(MAX($B$5:$B$23)-B9)/(MAX($B$5:$B$23)-MIN($B$5:$B$23)) -> 0.55969517 | K9: =(C9-MIN($C$5:$C$23))/(MAX($C$5:$C$23)-MIN($C$5:$C$23)) -> 0 | L9: =(MAX($D$5:$D$23)-D9)/(MAX($D$5:$D$23)-MIN($D$5:$D$23)) -> 0.86125 | M9: =(LN(E9)-LN(MIN($E$5:$E$23)))/(LN(MAX($E$5:$E$23))-LN(MIN($E$5:$E$23))) -> 0 | N9: =(F9-MIN($F$5:$F$23))/(MAX($F$5:$F$23)-MIN($F$5:$F$23)) -> 0.24848485 | O9: =(MAX($G$5:$G$23)-G9)/(MAX($G$5:$G$23)-MIN($G$5:$G$23)) -> 1 | P9: =(MAX($H$5:$H$23)-H9)/(MAX($H$5:$H$23)-MIN($H$5:$H$23)) -> 0.9978355 | Q9: =(MAX($I$5:$I$23)-I9)/(MAX($I$5:$I$23)-MIN($I$5:$I$23)) -> 1 | R9: =100*SUMPRODUCT(J9:P9,Weights!$B$4:$H$4) -> 51.907198 | S9: =RANK(R9,$R$5:$R$23,0) -> 8 | T9: =100*SUMPRODUCT(J9:P9,Weights!$B$5:$H$5) -> 52.405224 | U9: =RANK(T9,$T$5:$T$23,0) -> 6 | V9: =100*SUMPRODUCT(J9:P9,Weights!$B$6:$H$6) -> 58.313763 | W9: =RANK(V9,$V$5:$V$23,0) -> 3 | X9: =100*(SUMPRODUCT(J9:O9,Weights!$B$4:$G$4)+Q9*Weights!$H$4) -> 51.929536 | Y9: =RANK(X9,$X$5:$X$23,0) -> 9 | Z9: =(S9<=8)+(U9<=8)+(W9<=8)+(Y9<=8) -> 3 | AA9: =100*SUMPRODUCT(J9:P9,Weights!$B$7:$H$7) -> 52.807459 | AB9: =RANK(AA9,$AA$5:$AA$23,0) -> 6
A10: Gujarat | B10: =INDEX(Data_All!$F$5:$F$40,MATCH($A10,Data_All!$A$5:$A$40,0)) -> 55.95 | C10: =INDEX(Data_All!$G$5:$G$40,MATCH($A10,Data_All!$A$5:$A$40,0)) -> 11.28 | D10: =INDEX(Data_All!$J$5:$J$40,MATCH($A10,Data_All!$A$5:$A$40,0)) -> 6.22 | E10: =INDEX(Data_All!$H$5:$H$40,MATCH($A10,Data_All!$A$5:$A$40,0)) -> 151875 | F10: =INDEX(Data_All!$K$5:$K$40,MATCH($A10,Data_All!$A$5:$A$40,0)) -> 14.9 | G10: =INDEX(Data_All!$L$5:$L$40,MATCH($A10,Data_All!$A$5:$A$40,0)) -> 21805 | H10: =INDEX(Data_All!$M$5:$M$40,MATCH($A10,Data_All!$A$5:$A$40,0)) -> 3.66 | I10: =INDEX(Data_All!$N$5:$N$40,MATCH($A10,Data_All!$A$5:$A$40,0)) -> 27.44 | J10: =(MAX($B$5:$B$23)-B10)/(MAX($B$5:$B$23)-MIN($B$5:$B$23)) -> 0.29720576 | K10: =(C10-MIN($C$5:$C$23))/(MAX($C$5:$C$23)-MIN($C$5:$C$23)) -> 0.56021989 | L10: =(MAX($D$5:$D$23)-D10)/(MAX($D$5:$D$23)-MIN($D$5:$D$23)) -> 0.87 | M10: =(LN(E10)-LN(MIN($E$5:$E$23)))/(LN(MAX($E$5:$E$23))-LN(MIN($E$5:$E$23))) -> 0.90282794 | N10: =(F10-MIN($F$5:$F$23))/(MAX($F$5:$F$23)-MIN($F$5:$F$23)) -> 0.38787879 | O10: =(MAX($G$5:$G$23)-G10)/(MAX($G$5:$G$23)-MIN($G$5:$G$23)) -> 0.74231032 | P10: =(MAX($H$5:$H$23)-H10)/(MAX($H$5:$H$23)-MIN($H$5:$H$23)) -> 0.28138528 | Q10: =(MAX($I$5:$I$23)-I10)/(MAX($I$5:$I$23)-MIN($I$5:$I$23)) -> 0.61103032 | R10: =100*SUMPRODUCT(J10:P10,Weights!$B$4:$H$4) -> 56.479505 | S10: =RANK(R10,$R$5:$R$23,0) -> 3 | T10: =100*SUMPRODUCT(J10:P10,Weights!$B$5:$H$5) -> 57.757722 | U10: =RANK(T10,$T$5:$T$23,0) -> 2 | V10: =100*SUMPRODUCT(J10:P10,Weights!$B$6:$H$6) -> 54.040166 | W10: =RANK(V10,$V$5:$V$23,0) -> 7 | X10: =100*(SUMPRODUCT(J10:O10,Weights!$B$4:$G$4)+Q10*Weights!$H$4) -> 59.881442 | Y10: =RANK(X10,$X$5:$X$23,0) -> 2 | Z10: =(S10<=8)+(U10<=8)+(W10<=8)+(Y10<=8) -> 4 | AA10: =100*SUMPRODUCT(J10:P10,Weights!$B$7:$H$7) -> 53.887757 | AB10: =RANK(AA10,$AA$5:$AA$23,0) -> 5
A11: Himachal Pradesh | B11: =INDEX(Data_All!$F$5:$F$40,MATCH($A11,Data_All!$A$5:$A$40,0)) -> 38.5 | C11: =INDEX(Data_All!$G$5:$G$40,MATCH($A11,Data_All!$A$5:$A$40,0)) -> 0.62 | D11: =INDEX(Data_All!$J$5:$J$40,MATCH($A11,Data_All!$A$5:$A$40,0)) -> 8.07 | E11: =INDEX(Data_All!$H$5:$H$40,MATCH($A11,Data_All!$A$5:$A$40,0)) -> 13526 | F11: =INDEX(Data_All!$K$5:$K$40,MATCH($A11,Data_All!$A$5:$A$40,0)) -> 22.7 | G11: =INDEX(Data_All!$L$5:$L$40,MATCH($A11,Data_All!$A$5:$A$40,0)) -> 27878 | H11: =INDEX(Data_All!$M$5:$M$40,MATCH($A11,Data_All!$A$5:$A$40,0)) -> 3.03 | I11: =INDEX(Data_All!$N$5:$N$40,MATCH($A11,Data_All!$A$5:$A$40,0)) -> 15.63 | J11: =(MAX($B$5:$B$23)-B11)/(MAX($B$5:$B$23)-MIN($B$5:$B$23)) -> 0.59271804 | K11: =(C11-MIN($C$5:$C$23))/(MAX($C$5:$C$23)-MIN($C$5:$C$23)) -> 0.027486257 | L11: =(MAX($D$5:$D$23)-D11)/(MAX($D$5:$D$23)-MIN($D$5:$D$23)) -> 0.63875 | M11: =(LN(E11)-LN(MIN($E$5:$E$23)))/(LN(MAX($E$5:$E$23))-LN(MIN($E$5:$E$23))) -> 0.07536294 | N11: =(F11-MIN($F$5:$F$23))/(MAX($F$5:$F$23)-MIN($F$5:$F$23)) -> 0.86060606 | O11: =(MAX($G$5:$G$23)-G11)/(MAX($G$5:$G$23)-MIN($G$5:$G$23)) -> 0.22342789 | P11: =(MAX($H$5:$H$23)-H11)/(MAX($H$5:$H$23)-MIN($H$5:$H$23)) -> 0.55411255 | Q11: =(MAX($I$5:$I$23)-I11)/(MAX($I$5:$I$23)-MIN($I$5:$I$23)) -> 0.87526569 | R11: =100*SUMPRODUCT(J11:P11,Weights!$B$4:$H$4) -> 36.318378 | S11: =RANK(R11,$R$5:$R$23,0) -> 17 | T11: =100*SUMPRODUCT(J11:P11,Weights!$B$5:$H$5) -> 42.476507 | U11: =RANK(T11,$T$5:$T$23,0) -> 15 | V11: =100*SUMPRODUCT(J11:P11,Weights!$B$6:$H$6) -> 44.082204 | W11: =RANK(V11,$V$5:$V$23,0) -> 14 | X11: =100*(SUMPRODUCT(J11:O11,Weights!$B$4:$G$4)+Q11*Weights!$H$4) -> 39.632678 | Y11: =RANK(X11,$X$5:$X$23,0) -> 17 | Z11: =(S11<=8)+(U11<=8)+(W11<=8)+(Y11<=8) -> 0 | AA11: =100*SUMPRODUCT(J11:P11,Weights!$B$7:$H$7) -> 46.056592 | AB11: =RANK(AA11,$AA$5:$AA$23,0) -> 12
A12: Jammu and Kashmir | B12: =INDEX(Data_All!$F$5:$F$40,MATCH($A12,Data_All!$A$5:$A$40,0)) -> 24.73 | C12: =INDEX(Data_All!$G$5:$G$40,MATCH($A12,Data_All!$A$5:$A$40,0)) -> 1.56 | D12: =INDEX(Data_All!$J$5:$J$40,MATCH($A12,Data_All!$A$5:$A$40,0)) -> 5.18 | E12: =INDEX(Data_All!$H$5:$H$40,MATCH($A12,Data_All!$A$5:$A$40,0)) -> 20283 | F12: =INDEX(Data_All!$K$5:$K$40,MATCH($A12,Data_All!$A$5:$A$40,0)) -> 14.1 | G12: =INDEX(Data_All!$L$5:$L$40,MATCH($A12,Data_All!$A$5:$A$40,0)) -> 29088 | H12: =INDEX(Data_All!$M$5:$M$40,MATCH($A12,Data_All!$A$5:$A$40,0)) -> 2.26 | I12: =INDEX(Data_All!$N$5:$N$40,MATCH($A12,Data_All!$A$5:$A$40,0)) -> 14.56 | J12: =(MAX($B$5:$B$23)-B12)/(MAX($B$5:$B$23)-MIN($B$5:$B$23)) -> 0.82591025 | K12: =(C12-MIN($C$5:$C$23))/(MAX($C$5:$C$23)-MIN($C$5:$C$23)) -> 0.074462769 | L12: =(MAX($D$5:$D$23)-D12)/(MAX($D$5:$D$23)-MIN($D$5:$D$23)) -> 1 | M12: =(LN(E12)-LN(MIN($E$5:$E$23)))/(LN(MAX($E$5:$E$23))-LN(MIN($E$5:$E$23))) -> 0.21399069 | N12: =(F12-MIN($F$5:$F$23))/(MAX($F$5:$F$23)-MIN($F$5:$F$23)) -> 0.33939394 | O12: =(MAX($G$5:$G$23)-G12)/(MAX($G$5:$G$23)-MIN($G$5:$G$23)) -> 0.12004443 | P12: =(MAX($H$5:$H$23)-H12)/(MAX($H$5:$H$23)-MIN($H$5:$H$23)) -> 0.88744589 | Q12: =(MAX($I$5:$I$23)-I12)/(MAX($I$5:$I$23)-MIN($I$5:$I$23)) -> 0.89920573 | R12: =100*SUMPRODUCT(J12:P12,Weights!$B$4:$H$4) -> 44.309828 | S12: =RANK(R12,$R$5:$R$23,0) -> 11 | T12: =100*SUMPRODUCT(J12:P12,Weights!$B$5:$H$5) -> 49.461233 | U12: =RANK(T12,$T$5:$T$23,0) -> 9 | V12: =100*SUMPRODUCT(J12:P12,Weights!$B$6:$H$6) -> 54.358673 | W12: =RANK(V12,$V$5:$V$23,0) -> 6 | X12: =100*(SUMPRODUCT(J12:O12,Weights!$B$4:$G$4)+Q12*Weights!$H$4) -> 44.43119 | Y12: =RANK(X12,$X$5:$X$23,0) -> 12 | Z12: =(S12<=8)+(U12<=8)+(W12<=8)+(Y12<=8) -> 1 | AA12: =100*SUMPRODUCT(J12:P12,Weights!$B$7:$H$7) -> 54.378095 | AB12: =RANK(AA12,$AA$5:$AA$23,0) -> 4
A13: Jharkhand | B13: =INDEX(Data_All!$F$5:$F$40,MATCH($A13,Data_All!$A$5:$A$40,0)) -> 32.89 | C13: =INDEX(Data_All!$G$5:$G$40,MATCH($A13,Data_All!$A$5:$A$40,0)) -> 3.78 | D13: =INDEX(Data_All!$J$5:$J$40,MATCH($A13,Data_All!$A$5:$A$40,0)) -> 8.82 | E13: =INDEX(Data_All!$H$5:$H$40,MATCH($A13,Data_All!$A$5:$A$40,0)) -> 15126 | F13: =INDEX(Data_All!$K$5:$K$40,MATCH($A13,Data_All!$A$5:$A$40,0)) -> 9.9 | G13: =INDEX(Data_All!$L$5:$L$40,MATCH($A13,Data_All!$A$5:$A$40,0)) -> 30055 | H13: =INDEX(Data_All!$M$5:$M$40,MATCH($A13,Data_All!$A$5:$A$40,0)) -> 2.46 | I13: =INDEX(Data_All!$N$5:$N$40,MATCH($A13,Data_All!$A$5:$A$40,0)) -> 17.03 | J13: =(MAX($B$5:$B$23)-B13)/(MAX($B$5:$B$23)-MIN($B$5:$B$23)) -> 0.68772227 | K13: =(C13-MIN($C$5:$C$23))/(MAX($C$5:$C$23)-MIN($C$5:$C$23)) -> 0.1854073 | L13: =(MAX($D$5:$D$23)-D13)/(MAX($D$5:$D$23)-MIN($D$5:$D$23)) -> 0.545 | M13: =(LN(E13)-LN(MIN($E$5:$E$23)))/(LN(MAX($E$5:$E$23))-LN(MIN($E$5:$E$23))) -> 0.11361551 | N13: =(F13-MIN($F$5:$F$23))/(MAX($F$5:$F$23)-MIN($F$5:$F$23)) -> 0.084848485 | O13: =(MAX($G$5:$G$23)-G13)/(MAX($G$5:$G$23)-MIN($G$5:$G$23)) -> 0.037423103 | P13: =(MAX($H$5:$H$23)-H13)/(MAX($H$5:$H$23)-MIN($H$5:$H$23)) -> 0.8008658 | Q13: =(MAX($I$5:$I$23)-I13)/(MAX($I$5:$I$23)-MIN($I$5:$I$23)) -> 0.84394228 | R13: =100*SUMPRODUCT(J13:P13,Weights!$B$4:$H$4) -> 34.086883 | S13: =RANK(R13,$R$5:$R$23,0) -> 18 | T13: =100*SUMPRODUCT(J13:P13,Weights!$B$5:$H$5) -> 35.08027 | U13: =RANK(T13,$T$5:$T$23,0) -> 19 | V13: =100*SUMPRODUCT(J13:P13,Weights!$B$6:$H$6) -> 40.696853 | W13: =RANK(V13,$V$5:$V$23,0) -> 16 | X13: =100*(SUMPRODUCT(J13:O13,Weights!$B$4:$G$4)+Q13*Weights!$H$4) -> 34.531432 | Y13: =RANK(X13,$X$5:$X$23,0) -> 18 | Z13: =(S13<=8)+(U13<=8)+(W13<=8)+(Y13<=8) -> 0 | AA13: =100*SUMPRODUCT(J13:P13,Weights!$B$7:$H$7) -> 39.506655 | AB13: =RANK(AA13,$AA$5:$AA$23,0) -> 18
A14: Karnataka | B14: =INDEX(Data_All!$F$5:$F$40,MATCH($A14,Data_All!$A$5:$A$40,0)) -> 66.49 | C14: =INDEX(Data_All!$G$5:$G$40,MATCH($A14,Data_All!$A$5:$A$40,0)) -> 5.83 | D14: =INDEX(Data_All!$J$5:$J$40,MATCH($A14,Data_All!$A$5:$A$40,0)) -> 8.1 | E14: =INDEX(Data_All!$H$5:$H$40,MATCH($A14,Data_All!$A$5:$A$40,0)) -> 92446 | F14: =INDEX(Data_All!$K$5:$K$40,MATCH($A14,Data_All!$A$5:$A$40,0)) -> 17.4 | G14: =INDEX(Data_All!$L$5:$L$40,MATCH($A14,Data_All!$A$5:$A$40,0)) -> 30471 | H14: =INDEX(Data_All!$M$5:$M$40,MATCH($A14,Data_All!$A$5:$A$40,0)) -> 2.78 | I14: =INDEX(Data_All!$N$5:$N$40,MATCH($A14,Data_All!$A$5:$A$40,0)) -> 29.82 | J14: =(MAX($B$5:$B$23)-B14)/(MAX($B$5:$B$23)-MIN($B$5:$B$23)) -> 0.11871296 | K14: =(C14-MIN($C$5:$C$23))/(MAX($C$5:$C$23)-MIN($C$5:$C$23)) -> 0.28785607 | L14: =(MAX($D$5:$D$23)-D14)/(MAX($D$5:$D$23)-MIN($D$5:$D$23)) -> 0.635 | M14: =(LN(E14)-LN(MIN($E$5:$E$23)))/(LN(MAX($E$5:$E$23))-LN(MIN($E$5:$E$23))) -> 0.73297451 | N14: =(F14-MIN($F$5:$F$23))/(MAX($F$5:$F$23)-MIN($F$5:$F$23)) -> 0.53939394 | O14: =(MAX($G$5:$G$23)-G14)/(MAX($G$5:$G$23)-MIN($G$5:$G$23)) -> 0.0018796992 | P14: =(MAX($H$5:$H$23)-H14)/(MAX($H$5:$H$23)-MIN($H$5:$H$23)) -> 0.66233766 | Q14: =(MAX($I$5:$I$23)-I14)/(MAX($I$5:$I$23)-MIN($I$5:$I$23)) -> 0.55778051 | R14: =100*SUMPRODUCT(J14:P14,Weights!$B$4:$H$4) -> 33.124612 | S14: =RANK(R14,$R$5:$R$23,0) -> 19 | T14: =100*SUMPRODUCT(J14:P14,Weights!$B$5:$H$5) -> 42.557833 | U14: =RANK(T14,$T$5:$T$23,0) -> 14 | V14: =100*SUMPRODUCT(J14:P14,Weights!$B$6:$H$6) -> 45.506156 | W14: =RANK(V14,$V$5:$V$23,0) -> 13 | X14: =100*(SUMPRODUCT(J14:O14,Weights!$B$4:$G$4)+Q14*Weights!$H$4) -> 32.045582 | Y14: =RANK(X14,$X$5:$X$23,0) -> 19 | Z14: =(S14<=8)+(U14<=8)+(W14<=8)+(Y14<=8) -> 0 | AA14: =100*SUMPRODUCT(J14:P14,Weights!$B$7:$H$7) -> 41.591616 | AB14: =RANK(AA14,$AA$5:$AA$23,0) -> 15
A15: Kerala | B15: =INDEX(Data_All!$F$5:$F$40,MATCH($A15,Data_All!$A$5:$A$40,0)) -> 49.95 | C15: =INDEX(Data_All!$G$5:$G$40,MATCH($A15,Data_All!$A$5:$A$40,0)) -> 2.47 | D15: =INDEX(Data_All!$J$5:$J$40,MATCH($A15,Data_All!$A$5:$A$40,0)) -> 7.63 | E15: =INDEX(Data_All!$H$5:$H$40,MATCH($A15,Data_All!$A$5:$A$40,0)) -> 31616 | F15: =INDEX(Data_All!$K$5:$K$40,MATCH($A15,Data_All!$A$5:$A$40,0)) -> 25 | G15: =INDEX(Data_All!$L$5:$L$40,MATCH($A15,Data_All!$A$5:$A$40,0)) -> 28475 | H15: =INDEX(Data_All!$M$5:$M$40,MATCH($A15,Data_All!$A$5:$A$40,0)) -> 2.97 | I15: =INDEX(Data_All!$N$5:$N$40,MATCH($A15,Data_All!$A$5:$A$40,0)) -> 13.75 | J15: =(MAX($B$5:$B$23)-B15)/(MAX($B$5:$B$23)-MIN($B$5:$B$23)) -> 0.39881456 | K15: =(C15-MIN($C$5:$C$23))/(MAX($C$5:$C$23)-MIN($C$5:$C$23)) -> 0.11994003 | L15: =(MAX($D$5:$D$23)-D15)/(MAX($D$5:$D$23)-MIN($D$5:$D$23)) -> 0.69375 | M15: =(LN(E15)-LN(MIN($E$5:$E$23)))/(LN(MAX($E$5:$E$23))-LN(MIN($E$5:$E$23))) -> 0.36586327 | N15: =(F15-MIN($F$5:$F$23))/(MAX($F$5:$F$23)-MIN($F$5:$F$23)) -> 1 | O15: =(MAX($G$5:$G$23)-G15)/(MAX($G$5:$G$23)-MIN($G$5:$G$23)) -> 0.17241969 | P15: =(MAX($H$5:$H$23)-H15)/(MAX($H$5:$H$23)-MIN($H$5:$H$23)) -> 0.58008658 | Q15: =(MAX($I$5:$I$23)-I15)/(MAX($I$5:$I$23)-MIN($I$5:$I$23)) -> 0.91732856 | R15: =100*SUMPRODUCT(J15:P15,Weights!$B$4:$H$4) -> 38.113176 | S15: =RANK(R15,$R$5:$R$23,0) -> 16 | T15: =100*SUMPRODUCT(J15:P15,Weights!$B$5:$H$5) -> 47.598191 | U15: =RANK(T15,$T$5:$T$23,0) -> 11 | V15: =100*SUMPRODUCT(J15:P15,Weights!$B$6:$H$6) -> 48.887009 | W15: =RANK(V15,$V$5:$V$23,0) -> 9 | X15: =100*(SUMPRODUCT(J15:O15,Weights!$B$4:$G$4)+Q15*Weights!$H$4) -> 41.593513 | Y15: =RANK(X15,$X$5:$X$23,0) -> 14 | Z15: =(S15<=8)+(U15<=8)+(W15<=8)+(Y15<=8) -> 0 | AA15: =100*SUMPRODUCT(J15:P15,Weights!$B$7:$H$7) -> 49.26577 | AB15: =RANK(AA15,$AA$5:$AA$23,0) -> 10
A16: Madhya Pradesh | B16: =INDEX(Data_All!$F$5:$F$40,MATCH($A16,Data_All!$A$5:$A$40,0)) -> 59.32 | C16: =INDEX(Data_All!$G$5:$G$40,MATCH($A16,Data_All!$A$5:$A$40,0)) -> 13.89 | D16: =INDEX(Data_All!$J$5:$J$40,MATCH($A16,Data_All!$A$5:$A$40,0)) -> 8.73 | E16: =INDEX(Data_All!$H$5:$H$40,MATCH($A16,Data_All!$A$5:$A$40,0)) -> 104312 | F16: =INDEX(Data_All!$K$5:$K$40,MATCH($A16,Data_All!$A$5:$A$40,0)) -> 12.7 | G16: =INDEX(Data_All!$L$5:$L$40,MATCH($A16,Data_All!$A$5:$A$40,0)) -> 22768 | H16: =INDEX(Data_All!$M$5:$M$40,MATCH($A16,Data_All!$A$5:$A$40,0)) -> 2.81 | I16: =INDEX(Data_All!$N$5:$N$40,MATCH($A16,Data_All!$A$5:$A$40,0)) -> 30.79 | J16: =(MAX($B$5:$B$23)-B16)/(MAX($B$5:$B$23)-MIN($B$5:$B$23)) -> 0.24013548 | K16: =(C16-MIN($C$5:$C$23))/(MAX($C$5:$C$23)-MIN($C$5:$C$23)) -> 0.69065467 | L16: =(MAX($D$5:$D$23)-D16)/(MAX($D$5:$D$23)-MIN($D$5:$D$23)) -> 0.55625 | M16: =(LN(E16)-LN(MIN($E$5:$E$23)))/(LN(MAX($E$5:$E$23))-LN(MIN($E$5:$E$23))) -> 0.77429285 | N16: =(F16-MIN($F$5:$F$23))/(MAX($F$5:$F$23)-MIN($F$5:$F$23)) -> 0.25454545 | O16: =(MAX($G$5:$G$23)-G16)/(MAX($G$5:$G$23)-MIN($G$5:$G$23)) -> 0.66003076 | P16: =(MAX($H$5:$H$23)-H16)/(MAX($H$5:$H$23)-MIN($H$5:$H$23)) -> 0.64935065 | Q16: =(MAX($I$5:$I$23)-I16)/(MAX($I$5:$I$23)-MIN($I$5:$I$23)) -> 0.53607786 | R16: =100*SUMPRODUCT(J16:P16,Weights!$B$4:$H$4) -> 54.827439 | S16: =RANK(R16,$R$5:$R$23,0) -> 6 | T16: =100*SUMPRODUCT(J16:P16,Weights!$B$5:$H$5) -> 54.662963 | U16: =RANK(T16,$T$5:$T$23,0) -> 4 | V16: =100*SUMPRODUCT(J16:P16,Weights!$B$6:$H$6) -> 55.932631 | W16: =RANK(V16,$V$5:$V$23,0) -> 4 | X16: =100*(SUMPRODUCT(J16:O16,Weights!$B$4:$G$4)+Q16*Weights!$H$4) -> 53.658464 | Y16: =RANK(X16,$X$5:$X$23,0) -> 6 | Z16: =(S16<=8)+(U16<=8)+(W16<=8)+(Y16<=8) -> 4 | AA16: =100*SUMPRODUCT(J16:P16,Weights!$B$7:$H$7) -> 51.407957 | AB16: =RANK(AA16,$AA$5:$AA$23,0) -> 8
... A23: West Bengal | B23: =INDEX(Data_All!$F$5:$F$40,MATCH($A23,Data_All!$A$5:$A$40,0)) -> 45.19 | C23: =INDEX(Data_All!$G$5:$G$40,MATCH($A23,Data_All!$A$5:$A$40,0)) -> 12.88 | D23: =INDEX(Data_All!$J$5:$J$40,MATCH($A23,Data_All!$A$5:$A$40,0)) -> 9.04 | E23: =INDEX(Data_All!$H$5:$H$40,MATCH($A23,Data_All!$A$5:$A$40,0)) -> 71085 | F23: =INDEX(Data_All!$K$5:$K$40,MATCH($A23,Data_All!$A$5:$A$40,0)) -> 10.9 | G23: =INDEX(Data_All!$L$5:$L$40,MATCH($A23,Data_All!$A$5:$A$40,0)) -> 19019 | H23: =INDEX(Data_All!$M$5:$M$40,MATCH($A23,Data_All!$A$5:$A$40,0)) -> 4.31 | I23: =INDEX(Data_All!$N$5:$N$40,MATCH($A23,Data_All!$A$5:$A$40,0)) -> 51.78 | J23: =(MAX($B$5:$B$23)-B23)/(MAX($B$5:$B$23)-MIN($B$5:$B$23)) -> 0.47942422 | K23: =(C23-MIN($C$5:$C$23))/(MAX($C$5:$C$23)-MIN($C$5:$C$23)) -> 0.64017991 | L23: =(MAX($D$5:$D$23)-D23)/(MAX($D$5:$D$23)-MIN($D$5:$D$23)) -> 0.5175 | M23: =(LN(E23)-LN(MIN($E$5:$E$23)))/(LN(MAX($E$5:$E$23))-LN(MIN($E$5:$E$23))) -> 0.64307577 | N23: =(F23-MIN($F$5:$F$23))/(MAX($F$5:$F$23)-MIN($F$5:$F$23)) -> 0.14545455 | O23: =(MAX($G$5:$G$23)-G23)/(MAX($G$5:$G$23)-MIN($G$5:$G$23)) -> 0.9803486 | P23: =(MAX($H$5:$H$23)-H23)/(MAX($H$5:$H$23)-MIN($H$5:$H$23)) -> 0 | Q23: =(MAX($I$5:$I$23)-I23)/(MAX($I$5:$I$23)-MIN($I$5:$I$23)) -> 0.066450386 | R23: =100*SUMPRODUCT(J23:P23,Weights!$B$4:$H$4) -> 56.217669 | S23: =RANK(R23,$R$5:$R$23,0) -> 4 | T23: =100*SUMPRODUCT(J23:P23,Weights!$B$5:$H$5) -> 48.671498 | U23: =RANK(T23,$T$5:$T$23,0) -> 10 | V23: =100*SUMPRODUCT(J23:P23,Weights!$B$6:$H$6) -> 42.574788 | W23: =RANK(V23,$V$5:$V$23,0) -> 15 | X23: =100*(SUMPRODUCT(J23:O23,Weights!$B$4:$G$4)+Q23*Weights!$H$4) -> 56.903437 | Y23: =RANK(X23,$X$5:$X$23,0) -> 4 | Z23: =(S23<=8)+(U23<=8)+(W23<=8)+(Y23<=8) -> 2 | AA23: =100*SUMPRODUCT(J23:P23,Weights!$B$7:$H$7) -> 45.369745 | AB23: =RANK(AA23,$AA$5:$AA$23,0) -> 13
A25: Raw values above are linked; changing Data_All or Weights re-ranks automatically. Top 8 in = number of the four schemes (PCA, equal, pillar, DRI-swap) placing the state in the top eight.

Sheet Sources
A1: Sources
A3: Indicator | B3: Source | C3: Period | D3: Notes
A4: Groundwater (recharge, extractable, extraction, stage) | B4: Ministry of Jal Shakti, Lok Sabha reply; PIB release 2206073 (18 Dec 2025), Annexure-I — Dynamic Ground Water Resources of India 2025 (CGWB) | C4: 2025 | D4: State totals; district hotspots not reflected
A5: Power supplied, shortfall | B5: CEA power supply position via Ministry of Power, Rajya Sabha Unstarred Q. 1752 (4 Aug 2025), Annexure-III | C5: FY 2024-25 | D5: Same CEA series reproduced in RBI Handbook of Statistics on Indian States (availability of power); RBI site blocked automated download
A6: Industrial tariff | B6: CEA, Electricity Tariff & Duty and Average Rates of Electricity Supply in India, March 2026, Table 7(f): Large industries 20,000 kW, 60% LF, 33 kV, incl. duty | C6: Tariffs effective 2025-26 | D6: data.gov.in tariff dataset last updated 2013, so latest CEA edition used; Delhi rate from Oct 2021 order
A7: Skilled share | B7: PLFS Annual Report 2025 (MoSPI/NSO), Appendix A Table 8, rural+urban persons 15+: diploma/certificate + graduate + postgraduate & above | C7: Jan–Dec 2025 | D7: Share, not absolute pool size
A8: Wage cost | B8: PLFS Annual Report 2025, Appendix A Table 38, urban person average wage/salary earnings of regular wage/salaried employees (CWS) | C8: Jan–Dec 2025 | D8: Average across occupations, not data-centre specific
A9: Hazard index; Disaster Risk Index | B9: MHA–UNDP Disaster Score Card study (P.G. Dhar Chakrabarti), 'Measuring Disaster Risks and Resilience at Sub-National Level in India', Table 1.6 | C9: Pre-2019 | D9: Ladakh uses J&K values; DNH&DD averaged; NDM portal copy unavailable at time of access (preventionweb copy used)
A10: Data-centre hubs | B10: CEEW, Scaling India's Data Centre Ecosystem (Sept 2026), Figure 2, from Data Center Map, CBRE H1 2025, Savills | C10: Jan 2026 | D10: Used for narrative, not in index
A11: Capacity outlook | B11: JLL India data centre mid-year report 2026 | C11: Mid-2026 | D11: 1.6 GW to 6 GW by 2029
